ls_inspection_archive/__init__.py
ls_inspection_archive/client.py
ls_inspection_archive/models.py
ls_inspection_archive-0.1.0.dist-info/METADATA
ls_inspection_archive-0.1.0.dist-info/WHEEL
ls_inspection_archive-0.1.0.dist-info/top_level.txt
ls_inspection_archive-0.1.0.dist-info/RECORD
